<annotation>
	<folder>empty</folder>
	<filename>tytyt (19).png</filename>
	<path>C:\Users\swrig\StudioProjects\set_solver\training_model\dataSET\two\red\oval\empty\tytyt (19).png</path>
	<source>
		<database>Unknown</database>
	</source>
	<size>
		<width>94</width>
		<height>53</height>
		<depth>3</depth>
	</size>
	<segmented>0</segmented>
	<object>
		<name>two red oval empty</name>
		<pose>Unspecified</pose>
		<truncated>1</truncated>
		<difficult>0</difficult>
		<bndbox>
			<xmin>16</xmin>
			<ymin>1</ymin>
			<xmax>75</xmax>
			<ymax>47</ymax>
		</bndbox>
	</object>
</annotation>
