<annotation>
	<folder>one\purple\squiggle\empty</folder>
	<filename>one_purple_squiggle_empty_old (7).jpg</filename>
	<path>C:\Users\swrig\StudioProjects\set_solver\training_model\dataSET\one\purple\squiggle\empty\old (7).png</path>
	<source>
		<database>Unknown</database>
	</source>
	<size>
		<width>131</width>
		<height>86</height>
		<depth>3</depth>
	</size>
	<segmented>0</segmented>
	<object>
		<name>one purple squiggle empty</name>
		<pose>Unspecified</pose>
		<truncated>0</truncated>
		<difficult>0</difficult>
		<bndbox>
			<xmin>46</xmin>
			<ymin>14</ymin>
			<xmax>84</xmax>
			<ymax>77</ymax>
		</bndbox>
	</object>
</annotation>