<annotation>
	<folder>partial</folder>
	<filename>39.png</filename>
	<path>C:\Users\swrig\StudioProjects\set_solver\training_model\dataSET\one\green\diamond\partial\39.png</path>
	<source>
		<database>Unknown</database>
	</source>
	<size>
		<width>107</width>
		<height>68</height>
		<depth>3</depth>
	</size>
	<segmented>0</segmented>
	<object>
		<name>one green diamond partial</name>
		<pose>Unspecified</pose>
		<truncated>0</truncated>
		<difficult>0</difficult>
		<bndbox>
			<xmin>36</xmin>
			<ymin>5</ymin>
			<xmax>66</xmax>
			<ymax>60</ymax>
		</bndbox>
	</object>
</annotation>
