<annotation>
	<folder>partial</folder>
	<filename>z (1).png</filename>
	<path>C:\Users\swrig\StudioProjects\set_solver\training_model\dataSET\one\green\diamond\partial\z (1).png</path>
	<source>
		<database>Unknown</database>
	</source>
	<size>
		<width>128</width>
		<height>86</height>
		<depth>3</depth>
	</size>
	<segmented>0</segmented>
	<object>
		<name>one green diamond partial</name>
		<pose>Unspecified</pose>
		<truncated>0</truncated>
		<difficult>0</difficult>
		<bndbox>
			<xmin>47</xmin>
			<ymin>11</ymin>
			<xmax>80</xmax>
			<ymax>76</ymax>
		</bndbox>
	</object>
</annotation>
