<annotation>
	<folder>full</folder>
	<filename>568.png</filename>
	<path>C:\Users\swrig\StudioProjects\set_solver\training_model\dataSET\three\purple\squiggle\full\568.png</path>
	<source>
		<database>Unknown</database>
	</source>
	<size>
		<width>113</width>
		<height>72</height>
		<depth>3</depth>
	</size>
	<segmented>0</segmented>
	<object>
		<name>three purple squiggle full</name>
		<pose>Unspecified</pose>
		<truncated>0</truncated>
		<difficult>0</difficult>
		<bndbox>
			<xmin>9</xmin>
			<ymin>3</ymin>
			<xmax>106</xmax>
			<ymax>68</ymax>
		</bndbox>
	</object>
</annotation>
