<annotation>
	<folder>one\purple\squiggle\full</folder>
	<filename>one_purple_squiggle_full_09 (53).jpg</filename>
	<path>C:\Users\swrig\StudioProjects\set_solver\training_model\dataSET\one\purple\squiggle\full\09 (53).png</path>
	<source>
		<database>Unknown</database>
	</source>
	<size>
		<width>110</width>
		<height>65</height>
		<depth>3</depth>
	</size>
	<segmented>0</segmented>
	<object>
		<name>one purple squiggle full</name>
		<pose>Unspecified</pose>
		<truncated>0</truncated>
		<difficult>0</difficult>
		<bndbox>
			<xmin>38</xmin>
			<ymin>5</ymin>
			<xmax>71</xmax>
			<ymax>56</ymax>
		</bndbox>
	</object>
</annotation>